pygode/__init__.py
pygode/layout.py
pygode/methods.py
pygode-2.1.4.dist-info/METADATA
pygode-2.1.4.dist-info/WHEEL
pygode-2.1.4.dist-info/licenses/LICENSE
pygode-2.1.4.dist-info/RECORD
