Metadata-Version: 2.1
Name: pygode
Version: 2.1.4
Summary: Python package that converts gibberish caused by Thai user forgetting to change their keyboard layout.
Project-URL: Homepage, https://github.com/godeProject/pygode
Project-URL: Bug Tracker, https://github.com/godeProject/pygode/issues
Author-email: Jakkaphat Chalermphanaphan <gunt@guntxjakka.me>
License-Expression: MIT
License-File: LICENSE
Classifier: License :: OSI Approved :: MIT License
Classifier: Operating System :: OS Independent
Classifier: Programming Language :: Python :: 3
Requires-Python: >=3.8
